azureml/__init__.py
azureml/featurestore/__init__.py
azureml/featurestore/_feature_set.py
azureml/featurestore/_version.py
azureml/featurestore/abstract_feature_store.py
azureml/featurestore/feature_set_spec.py
azureml/featurestore/feature_store_client.py
azureml/featurestore/_offline_query/__init__.py
azureml/featurestore/_offline_query/dsl_feathr_retrieval_job.py
azureml/featurestore/_offline_query/dsl_feathr_shim_retrieval_job.py
azureml/featurestore/_offline_query/equal_time.py
azureml/featurestore/_offline_query/offline_retrieval_job.py
azureml/featurestore/_offline_query/point_at_time.py
azureml/featurestore/_online_query/__init__.py
azureml/featurestore/_online_query/online_retrieval_job.py
azureml/featurestore/_online_query/point_at_time.py
azureml/featurestore/_utils/__init__.py
azureml/featurestore/_utils/_constants.py
azureml/featurestore/_utils/_preview_method.py
azureml/featurestore/_utils/arm_id_utils.py
azureml/featurestore/_utils/dsl_utils.py
azureml/featurestore/_utils/error_constants.py
azureml/featurestore/_utils/materialize.py
azureml/featurestore/_utils/pandas_utils.py
azureml/featurestore/_utils/spark_utils.py
azureml/featurestore/_utils/type_map.py
azureml/featurestore/_utils/utils.py
azureml/featurestore/contracts/__init__.py
azureml/featurestore/contracts/column.py
azureml/featurestore/contracts/datetimeoffset.py
azureml/featurestore/contracts/feature.py
azureml/featurestore/contracts/feature_retrieval_spec.py
azureml/featurestore/contracts/feature_source.py
azureml/featurestore/contracts/feature_source_type.py
azureml/featurestore/contracts/feature_transformation.py
azureml/featurestore/contracts/join_type.py
azureml/featurestore/contracts/offline_store.py
azureml/featurestore/contracts/online_store.py
azureml/featurestore/contracts/partition.py
azureml/featurestore/contracts/store_connection.py
azureml/featurestore/contracts/timestamp_column.py
azureml/featurestore/contracts/transformation_code.py
azureml_featurestore-1.2.1.dist-info/METADATA
azureml_featurestore-1.2.1.dist-info/WHEEL
azureml_featurestore-1.2.1.dist-info/top_level.txt
azureml_featurestore-1.2.1.dist-info/RECORD
