Metadata-Version: 2.1
Name: azureml-featurestore
Version: 1.2.1
Summary: Azure Machine Learning Feature Store SDK
Home-page: https://aka.ms/featurestore-get-started
Author: Microsoft Corporation
Author-email: azuresdkengsysadmins@microsoft.com
License: MIT License
Keywords: AzureMachineLearning,azure,feature store
Classifier: Development Status :: 5 - Production/Stable
Classifier: Intended Audience :: Developers
Classifier: Natural Language :: English
Classifier: Operating System :: OS Independent
Classifier: Programming Language :: Python
Classifier: Programming Language :: Python :: 3
Classifier: Programming Language :: Python :: 3 :: Only
Classifier: Programming Language :: Python :: 3.8
Classifier: Programming Language :: Python :: 3.9
Classifier: Programming Language :: Python :: 3.10
Classifier: Programming Language :: Python :: 3.11
Classifier: Programming Language :: Python :: 3.12
Classifier: License :: OSI Approved :: MIT License
Requires-Python: <4.0,>=3.8
Requires-Dist: azure-ai-ml (<2.0.0,>=1.14.0)
Requires-Dist: mltable (<2.0.0,>=1.5.0)
Requires-Dist: jinja2 (<4.0.0,>=3.1.2)
Requires-Dist: marshmallow (<4.0.0,>=3.18.0)
Requires-Dist: pandas (>=1.5.3)
Provides-Extra: online
Requires-Dist: azure-identity ; extra == 'online'
Requires-Dist: azure-mgmt-redis (<15.0.0,>=14.1.0) ; extra == 'online'
Requires-Dist: azure-mgmt-redisenterprise (<3.1.0,>=3.0.0) ; extra == 'online'
Requires-Dist: pyarrow (>=9.0.0) ; extra == 'online'
Requires-Dist: redis (<5.3.0,>=5.2.1) ; extra == 'online'
Requires-Dist: msgpack (<2.0.0,>=1.0.5) ; extra == 'online'
